{
"type": "FeatureCollection",
"crs": { "type": "name", "properties": { "name": "urn:ogc:def:crs:OGC:1.3:CRS84" } },
"features": [
{ "type": "Feature", "properties": { "code": "301_CA_SNTL", "name": "Adin Mtn", "elevation_m": 1886.7120361328125, "latitude": 41.235828399658203, "longitude": -120.79192352294922, "county": "Modoc", "state": "California", "beginDate": "1983-10-01T00:00:00", "endDate": "2100-01-01T00:00:00", "isActive": true }, "geometry": { "type": "Point", "coordinates": [ -120.791923522949219, 41.235828399658203 ] } }
]
}
